Metadata-Version: 2.2
Name: dinoop_image_scan2
Version: 0.1.1
Summary: package for image scan
Author-email: dinoop <dinoop@example.com>
